[
  {
    "title": "Citizen Sleeper",
    "platform": "Epic Games",
    "original_price": "IDR 137,999",
    "thumbnail": "https://cdn1.epicgames.com/spt-assets/919d5976f3804d4cabb8ca90ea43a956/citizen-sleeper-a7mun.jpg",
    "url": "https://store.epicgames.com/en-US/p/citizen-sleeper-944858",
    "start_date": "2026-06-18T15:00:00.000Z",
    "end_date": "2026-06-25T15:00:00.000Z",
    "scraped_at": "2026-06-20T15:46:45Z"
  },
  {
    "title": "ROBOBEAT",
    "platform": "Epic Games",
    "original_price": "IDR 108,999",
    "thumbnail": "https://cdn1.epicgames.com/spt-assets/91105717b53044ed8e384e5fada71db8/robobeat-15z8d.png",
    "url": "https://store.epicgames.com/en-US/p/robobeat-5f084b",
    "start_date": "2026-06-18T15:00:00.000Z",
    "end_date": "2026-06-25T15:00:00.000Z",
    "scraped_at": "2026-06-20T15:46:45Z"
  },
  {
    "title": "RollerCoaster Tycoon 3 Complete Edition",
    "platform": "Epic Games",
    "original_price": "IDR 288,000",
    "thumbnail": "https://cdn1.epicgames.com/f01b3e0178d448f0b93911e292d8e614/offer/EGS_RollerCoasterTycoon3CompleteEdition_FrontierDevelopments_S6-1200x1600-591ca93f3bee7bc55a90b77ccc36eb84.jpg",
    "url": "https://store.epicgames.com/en-US/p/rollercoaster-tycoon-3-complete-edition",
    "start_date": "2026-06-25T15:00:00.000Z",
    "end_date": "2026-07-02T15:00:00.000Z",
    "scraped_at": "2026-06-26T06:10:12Z"
  },
  {
    "title": "Voidwrought",
    "platform": "Epic Games",
    "original_price": "IDR 137,999",
    "thumbnail": "https://cdn1.epicgames.com/spt-assets/ae3f962fab4d42eba2dbefa4a1e76ff6/voidwrought-9gwxt.png",
    "url": "https://store.epicgames.com/en-US/p/voidwrought-ce8f4b",
    "start_date": "2026-06-25T15:00:00.000Z",
    "end_date": "2026-07-02T15:00:00.000Z",
    "scraped_at": "2026-06-26T06:10:12Z"
  },
  {
    "title": "River City Girls 2",
    "platform": "Epic Games",
    "original_price": "IDR 276,999",
    "thumbnail": "https://cdn1.epicgames.com/spt-assets/dfdcd48c05c6483284cb40b333dc71e4/river-city-girls-2-12b0w.png",
    "url": "https://store.epicgames.com/en-US/p/river-city-girls-2-77af3a",
    "start_date": "2026-07-02T15:00:00.000Z",
    "end_date": "2026-07-09T15:00:00.000Z",
    "scraped_at": "2026-07-03T05:52:50Z"
  },
  {
    "title": "I Have No Mouth, and I Must Scream",
    "platform": "Epic Games",
    "original_price": "IDR 69,999",
    "thumbnail": "https://cdn1.epicgames.com/spt-assets/b153ccd09d834353a8f27ffa9b41f5a2/i-have-no-mouth-and-i-must-scream-1f2lo.png",
    "url": "https://store.epicgames.com/en-US/p/i-have-no-mouth-and-i-must-scream-95c5c2",
    "start_date": "2026-07-02T15:00:00.000Z",
    "end_date": "2026-07-09T15:00:00.000Z",
    "scraped_at": "2026-07-03T05:52:50Z"
  }
]